pyplusplus/__init__.py
pyplusplus/_logging_/__init__.py
pyplusplus/_logging_/multi_line_formatter.py
pyplusplus/binary_parsers/__init__.py
pyplusplus/binary_parsers/get_dll_exported_symbols.py
pyplusplus/binary_parsers/parsers.py
pyplusplus/binary_parsers/undname.py
pyplusplus/code_creators/__init__.py
pyplusplus/code_creators/algorithm.py
pyplusplus/code_creators/array_1_registrator.py
pyplusplus/code_creators/bookmark.py
pyplusplus/code_creators/calldef.py
pyplusplus/code_creators/calldef_ctypes.py
pyplusplus/code_creators/calldef_transformed.py
pyplusplus/code_creators/calldef_utils.py
pyplusplus/code_creators/class_declaration.py
pyplusplus/code_creators/code_creator.py
pyplusplus/code_creators/compound.py
pyplusplus/code_creators/ctypes_formatter.py
pyplusplus/code_creators/ctypes_integration_creators.py
pyplusplus/code_creators/custom.py
pyplusplus/code_creators/declaration_based.py
pyplusplus/code_creators/embedded_code_repository.py
pyplusplus/code_creators/enum.py
pyplusplus/code_creators/exception_translator.py
pyplusplus/code_creators/global_variable.py
pyplusplus/code_creators/include.py
pyplusplus/code_creators/include_directories.py
pyplusplus/code_creators/indexing_suites.py
pyplusplus/code_creators/instruction.py
pyplusplus/code_creators/library_reference.py
pyplusplus/code_creators/license.py
pyplusplus/code_creators/member_variable.py
pyplusplus/code_creators/module.py
pyplusplus/code_creators/module_body.py
pyplusplus/code_creators/name_mappings.py
pyplusplus/code_creators/namespace.py
pyplusplus/code_creators/opaque_type_registrator.py
pyplusplus/code_creators/properties.py
pyplusplus/code_creators/registration_based.py
pyplusplus/code_creators/scoped.py
pyplusplus/code_creators/smart_pointers.py
pyplusplus/code_creators/target_configuration.py
pyplusplus/code_creators/typedef_as_pyvar.py
pyplusplus/code_creators/unnamed_enum.py
pyplusplus/code_repository/__init__.py
pyplusplus/code_repository/array_1.py
pyplusplus-1.8.4.dist-info/LICENSE_1_0.txt
pyplusplus-1.8.4.dist-info/METADATA
pyplusplus-1.8.4.dist-info/WHEEL
pyplusplus-1.8.4.dist-info/top_level.txt
pyplusplus-1.8.4.dist-info/RECORD
