Metadata-Version: 2.1
Name: pyplusplus
Version: 1.8.4
Summary: Py++ is a framework of components for creating a C++ code generator using the Boost.Python library
Home-page: https://github.com/ompl/pyplusplus
Author: Roman Yakovenko
Author-email: roman.yakovenko@gmail.com
Maintainer: Mark Moll
Maintainer-email: mark.moll@gmail.com
License: Boost
Download-URL: https://github.com/ompl/pyplusplus/archive/1.8.4.zip
Keywords: C++,declaration parser,python bindings
Platform: UNKNOWN
Classifier: Development Status :: 5 - Production/Stable
Classifier: Environment :: Console
Classifier: Intended Audience :: Developers
Classifier: Operating System :: MacOS :: MacOS X
Classifier: Operating System :: Microsoft :: Windows
Classifier: Operating System :: POSIX
Classifier: Programming Language :: Python
Classifier: Topic :: Software Development
Requires-Dist: pygccxml
